StenLib/StenDecorators.py
StenLib/StenEnumUtils.py
StenLib/StenUtils.py
StenLib/__init__.py
StenLib/py.typed
StenLib/tests/__init__.py
StenLib/tests/test_StenDecorators.py
StenLib/tests/test_StenEnumUtils.py
StenLib/tests/test_StenUtils.py
StenLib-1.1.33.data/data/LICENSE.md
StenLib-1.1.33.data/data/README.md
StenLib-1.1.33.data/data/requirements.txt
StenLib-1.1.33.dist-info/LICENSE.md
StenLib-1.1.33.dist-info/METADATA
StenLib-1.1.33.dist-info/WHEEL
StenLib-1.1.33.dist-info/top_level.txt
StenLib-1.1.33.dist-info/RECORD
