Metadata-Version: 2.1
Name: StenLib
Version: 1.1.33
Home-page: https://github.com/Structura-Engineering/StenLib
License: GNU AFFERO GENERAL PUBLIC LICENSE
Project-URL: Bug Tracker, https://github.com/Structura-Engineering/StenLib/issues
Requires-Python: ==3.12.2
License-File: LICENSE.md
Requires-Dist: pytest
Requires-Dist: setuptools
